[{"_id": "Мадрид", "min_salary": 37989, "avg_salary": 111327.66666666667, "max_salary": "74325"}, {"_id": "Подгорица", "min_salary": 20404, "avg_salary": 87987.90909090909, "max_salary": "65186"}, {"_id": "Осера", "min_salary": 36173, "avg_salary": 109867.25, "max_salary": "97067"}, {"_id": "Трухильо", "min_salary": 30933, "avg_salary": 49276.181818181816, "max_salary": "98989"}, {"_id": "Будапешт", "min_salary": 37861, "avg_salary": 104073.25, "max_salary": "44296"}, {"_id": "Астана", "min_salary": 37835, "avg_salary": 115385.125, "max_salary": "98571"}, {"_id": "Аликанте", "min_salary": 31444, "avg_salary": 56204.4, "max_salary": "97877"}, {"_id": "Белград", "min_salary": 23189, "avg_salary": 110488.77777777778, "max_salary": "56459"}, {"_id": "Санхенхо", "min_salary": 28451, "avg_salary": 107258.75, "max_salary": "48815"}, {"_id": "Сан-Себастьян", "min_salary": 25869, "avg_salary": 94370.14285714286, "max_salary": "54282"}, {"_id": "Касерес", "min_salary": 45204, "avg_salary": 100888.6, "max_salary": "97910"}, {"_id": "Пласенсия", "min_salary": 49347, "avg_salary": 95304.2, "max_salary": "97383"}, {"_id": "Луго", "min_salary": 26781, "avg_salary": 121160.9, "max_salary": "64878"}, {"_id": "Артейхо", "min_salary": 22153, "avg_salary": 113692.28571428571, "max_salary": "95517"}, {"_id": "Кадакес", "min_salary": 49554, "avg_salary": 139843.16666666666, "max_salary": "95728"}, {"_id": "Ереван", "min_salary": 41260, "avg_salary": 111940.25, "max_salary": "84534"}, {"_id": "Душанбе", "min_salary": 59260, "avg_salary": 105678.66666666667, "max_salary": "48101"}, {"_id": "Санкт-Петербург", "min_salary": 70589, "avg_salary": 105559.6, "max_salary": "48131"}, {"_id": "Тбилиси", "min_salary": 61702, "avg_salary": 103744.75, "max_salary": "39138"}, {"_id": "Москва", "min_salary": 26166, "avg_salary": 121968.25, "max_salary": "78908"}, {"_id": "Алькала-де-Энарес", "min_salary": 39987, "avg_salary": 108508.33333333333, "max_salary": "85371"}, {"_id": "Валенсия", "min_salary": 21655, "avg_salary": 108419.57142857143, "max_salary": "99127"}, {"_id": "Гранада", "min_salary": 21898, "avg_salary": 96570.27272727272, "max_salary": "57029"}, {"_id": "Сория", "min_salary": 22528, "avg_salary": 107809.42857142857, "max_salary": "151241"}, {"_id": "Рига", "min_salary": 52887, "avg_salary": 119797.125, "max_salary": "48769"}, {"_id": "Минск", "min_salary": 21778, "avg_salary": 103015.375, "max_salary": "99989"}, {"_id": "Сеговия", "min_salary": 20676, "avg_salary": 81846.88888888889, "max_salary": "97218"}, {"_id": "Монсон", "min_salary": 74685, "avg_salary": 130986.42857142857, "max_salary": "69477"}, {"_id": "Севилья", "min_salary": 26511, "avg_salary": 105312.0, "max_salary": "84869"}, {"_id": "Тарраса", "min_salary": 22165, "avg_salary": 97645.57142857143, "max_salary": "98878"}, {"_id": "Авилес", "min_salary": 74528, "avg_salary": 104193.33333333333, "max_salary": "59748"}, {"_id": "Луарка", "min_salary": 22672, "avg_salary": 82998.5, "max_salary": "21747"}, {"_id": "Камбадос", "min_salary": 106366, "avg_salary": 148625.5, "max_salary": "80176"}, {"_id": "Картахена", "min_salary": 56887, "avg_salary": 135207.7, "max_salary": "95010"}, {"_id": "Таллин", "min_salary": 37035, "avg_salary": 79611.33333333333, "max_salary": "83027"}, {"_id": "Эльче", "min_salary": 22942, "avg_salary": 99845.5, "max_salary": "64499"}, {"_id": "Варшава", "min_salary": 40864, "avg_salary": 129207.28571428571, "max_salary": "92336"}, {"_id": "Самора", "min_salary": 49938, "avg_salary": 100550.85714285714, "max_salary": "75470"}, {"_id": "Махадаонда", "min_salary": 25586, "avg_salary": 125353.57142857143, "max_salary": "98530"}, {"_id": "Куэнка", "min_salary": 79234, "avg_salary": 133663.25, "max_salary": "65297"}, {"_id": "Хельсинки", "min_salary": 21982, "avg_salary": 116743.36363636363, "max_salary": "181742"}, {"_id": "Тудела", "min_salary": 34724, "avg_salary": 82596.4, "max_salary": "52312"}, {"_id": "Вильнюс", "min_salary": 42027, "avg_salary": 91225.66666666667, "max_salary": "80886"}, {"_id": "Барселона", "min_salary": 23088, "avg_salary": 110625.0, "max_salary": "98764"}, {"_id": "Овьедо", "min_salary": 52075, "avg_salary": 128661.125, "max_salary": "97249"}, {"_id": "Алма-Ата", "min_salary": 30388, "avg_salary": 110260.3, "max_salary": "97777"}, {"_id": "Лас-Росас", "min_salary": 39259, "avg_salary": 144807.16666666666, "max_salary": "98125"}, {"_id": "Хихон", "min_salary": 21471, "avg_salary": 95768.84615384616, "max_salary": "89465"}, {"_id": "Прага", "min_salary": 27355, "avg_salary": 85689.0, "max_salary": "55495"}, {"_id": "Вильявисиоса", "min_salary": 23051, "avg_salary": 91804.71428571429, "max_salary": "98650"}, {"_id": "Мерида", "min_salary": 23492, "avg_salary": 89890.125, "max_salary": "97775"}, {"_id": "Бишкек", "min_salary": 40843, "avg_salary": 84773.63636363637, "max_salary": "76347"}, {"_id": "Мартоса", "min_salary": 26312, "avg_salary": 108976.28571428571, "max_salary": "98340"}, {"_id": "Любляна", "min_salary": 45575, "avg_salary": 120219.44444444444, "max_salary": "87067"}, {"_id": "Льейда", "min_salary": 33787, "avg_salary": 103342.5, "max_salary": "95834"}, {"_id": "Вальядолид", "min_salary": 24117, "avg_salary": 122138.81818181818, "max_salary": "54507"}, {"_id": "София", "min_salary": 28911, "avg_salary": 92763.7, "max_salary": "98882"}, {"_id": "Афины", "min_salary": 40305, "avg_salary": 112617.0, "max_salary": "83687"}, {"_id": "Скопье", "min_salary": 23577, "avg_salary": 101929.33333333333, "max_salary": "83204"}, {"_id": "Тирана", "min_salary": 37084, "avg_salary": 123701.1, "max_salary": "87228"}, {"_id": "Семана", "min_salary": 26141, "avg_salary": 48771.5, "max_salary": "83697"}, {"_id": "Кишинев", "min_salary": 38380, "avg_salary": 71842.8, "max_salary": "148244"}, {"_id": "Кордова", "min_salary": 42047, "avg_salary": 89233.57142857143, "max_salary": "79779"}, {"_id": "Бильбао", "min_salary": 20976, "avg_salary": 97354.0, "max_salary": "86667"}, {"_id": "Сараево", "min_salary": 55060, "avg_salary": 121134.28571428571, "max_salary": "72739"}, {"_id": "Загреб", "min_salary": 24416, "avg_salary": 85606.92307692308, "max_salary": "54894"}, {"_id": "Вроцлав", "min_salary": 31464, "avg_salary": 119140.28571428571, "max_salary": "87786"}, {"_id": "Баку", "min_salary": 27387, "avg_salary": 100737.28571428571, "max_salary": "36665"}, {"_id": "Ла-Корунья", "min_salary": 34532, "avg_salary": 94733.16666666667, "max_salary": "96045"}, {"_id": "Ташкент", "min_salary": 34247, "avg_salary": 98567.6, "max_salary": "77260"}, {"_id": "Бланес", "min_salary": 69310, "avg_salary": 119809.66666666667, "max_salary": "28969"}, {"_id": "Краков", "min_salary": 40865, "avg_salary": 74071.22222222222, "max_salary": "58300"}, {"_id": "Навалькарнеро", "min_salary": 84358, "avg_salary": 137292.55555555556, "max_salary": "68210"}, {"_id": "Сьюдад-Реаль", "min_salary": 22403, "avg_salary": 124794.18181818182, "max_salary": "88973"}, {"_id": "Малага", "min_salary": 27103, "avg_salary": 86696.57142857143, "max_salary": "90054"}, {"_id": "Виго", "min_salary": 29858, "avg_salary": 95078.88888888889, "max_salary": "81839"}, {"_id": "Сантьяго-де-Компостела", "min_salary": 47760, "avg_salary": 126935.6, "max_salary": "96103"}, {"_id": "Мурсия", "min_salary": 29079, "avg_salary": 103360.28571428571, "max_salary": "69466"}, {"_id": "Эль-Пуэрто-де-Санта-Мария", "min_salary": 50516, "avg_salary": 115307.46153846153, "max_salary": "97731"}, {"_id": "Фигерас", "min_salary": 56368, "avg_salary": 121398.5, "max_salary": "74270"}, {"_id": "Бургос", "min_salary": 20491, "avg_salary": 83777.11111111111, "max_salary": "129201"}]